crowdai_repo2docker-0.5.0.dist-info/LICENSE.txt
crowdai_repo2docker-0.5.0.dist-info/METADATA
crowdai_repo2docker-0.5.0.dist-info/RECORD
crowdai_repo2docker-0.5.0.dist-info/WHEEL
crowdai_repo2docker-0.5.0.dist-info/entry_points.txt
crowdai_repo2docker-0.5.0.dist-info/top_level.txt
repo2docker/__init__.py
repo2docker/__main__.py
repo2docker/app.py
repo2docker/utils.py
repo2docker/buildpacks/__init__.py
repo2docker/buildpacks/base.py
repo2docker/buildpacks/docker.py
repo2docker/buildpacks/julia.py
repo2docker/buildpacks/r.py
repo2docker/buildpacks/__pycache__/__init__.cpython-36.pyc
repo2docker/buildpacks/__pycache__/base.cpython-36.pyc
repo2docker/buildpacks/__pycache__/docker.cpython-36.pyc
repo2docker/buildpacks/__pycache__/julia.cpython-36.pyc
repo2docker/buildpacks/__pycache__/r.cpython-36.pyc
repo2docker/buildpacks/conda/__init__.py
repo2docker/buildpacks/conda/environment.frozen.yml
repo2docker/buildpacks/conda/environment.py-2.7.frozen.yml
repo2docker/buildpacks/conda/environment.py-2.7.yml
repo2docker/buildpacks/conda/environment.py-3.5.frozen.yml
repo2docker/buildpacks/conda/environment.py-3.6.frozen.yml
repo2docker/buildpacks/conda/environment.yml
repo2docker/buildpacks/conda/freeze.py
repo2docker/buildpacks/conda/install-miniconda.bash
repo2docker/buildpacks/conda/__pycache__/__init__.cpython-36.pyc
repo2docker/buildpacks/legacy/__init__.py
repo2docker/buildpacks/legacy/freeze.py
repo2docker/buildpacks/legacy/python3.frozen.yml
repo2docker/buildpacks/legacy/python3.yml
repo2docker/buildpacks/legacy/root.frozen.yml
repo2docker/buildpacks/legacy/root.yml
repo2docker/buildpacks/legacy/__pycache__/__init__.cpython-36.pyc
repo2docker/buildpacks/python/__init__.py
repo2docker/buildpacks/python/__pycache__/__init__.cpython-36.pyc
