Metadata-Version: 2.1
Name: crowdai-repo2docker
Version: 0.5.0
Summary: UNKNOWN
Home-page: UNKNOWN
Author: Yuvi Panda
Author-email: yuvipanda@gmail.com
License: BSD
Platform: UNKNOWN
Requires-Python: >=3.4
Requires-Dist: docker
Requires-Dist: traitlets
Requires-Dist: python-json-logger
Requires-Dist: escapism
Requires-Dist: jinja2
Requires-Dist: ruamel.yaml (>=0.15)
